antplus/__init__.py
antplus/core.py
antplus-0.0.1.dist-info/LICENSE
antplus-0.0.1.dist-info/METADATA
antplus-0.0.1.dist-info/WHEEL
antplus-0.0.1.dist-info/top_level.txt
antplus-0.0.1.dist-info/RECORD
